{
    "authors": [
        {
            "name": "munichjake",
            "email": "munichjake@dnd-session.de",
            "url": "https://dnd-session.de",
            "github": "https://github.com/munichjake"
        }
    ],
    "description": "Fictional settlements of the human race",
    "version": "1.0.0",
    "settlements": [
        {
            "gender": "n",
            "name": "Alderdale"
        },
        {
            "gender": "n",
            "name": "Alderford"
        },
        {
            "gender": "n",
            "name": "Alderburg"
        },
        {
            "gender": "n",
            "name": "Alderbury"
        },
        {
            "gender": "n",
            "name": "Alderhaven"
        },
        {
            "gender": "n",
            "name": "Alderhelm"
        },
        {
            "gender": "n",
            "name": "Alderhold"
        },
        {
            "gender": "n",
            "name": "Alderholt"
        },
        {
            "gender": "n",
            "name": "Alderkeep"
        },
        {
            "gender": "n",
            "name": "Alderland"
        },
        {
            "gender": "n",
            "name": "Aldermarch"
        },
        {
            "gender": "n",
            "name": "Aldermere"
        },
        {
            "gender": "n",
            "name": "Aldermont"
        },
        {
            "gender": "n",
            "name": "Aldermoor"
        },
        {
            "gender": "n",
            "name": "Aldermouth"
        },
        {
            "gender": "n",
            "name": "Alderport"
        },
        {
            "gender": "n",
            "name": "Alderrest"
        },
        {
            "gender": "n",
            "name": "Alderstead"
        },
        {
            "gender": "n",
            "name": "Alderton"
        },
        {
            "gender": "n",
            "name": "Alderview"
        },
        {
            "gender": "n",
            "name": "Alderville"
        },
        {
            "gender": "n",
            "name": "Alderwatch"
        },
        {
            "gender": "n",
            "name": "Alderwick"
        },
        {
            "gender": "n",
            "name": "Alderworth"
        },
        {
            "gender": "n",
            "name": "Aldery"
        },
        {
            "gender": "n",
            "name": "Alderbay"
        },
        {
            "gender": "n",
            "name": "Alderbridge"
        },
        {
            "gender": "n",
            "name": "Aldercastle"
        },
        {
            "gender": "n",
            "name": "Aldercliff"
        },
        {
            "gender": "n",
            "name": "Aldercross"
        },
        {
            "gender": "n",
            "name": "Ashdale"
        },
        {
            "gender": "n",
            "name": "Ashford"
        },
        {
            "gender": "n",
            "name": "Ashburg"
        },
        {
            "gender": "n",
            "name": "Ashbury"
        },
        {
            "gender": "n",
            "name": "Ashhaven"
        },
        {
            "gender": "n",
            "name": "Ashhelm"
        },
        {
            "gender": "n",
            "name": "Ashhold"
        },
        {
            "gender": "n",
            "name": "Ashholt"
        },
        {
            "gender": "n",
            "name": "Ashkeep"
        },
        {
            "gender": "n",
            "name": "Ashland"
        },
        {
            "gender": "n",
            "name": "Ashmarch"
        },
        {
            "gender": "n",
            "name": "Ashmere"
        },
        {
            "gender": "n",
            "name": "Ashmont"
        },
        {
            "gender": "n",
            "name": "Ashmoor"
        },
        {
            "gender": "n",
            "name": "Ashmouth"
        },
        {
            "gender": "n",
            "name": "Ashport"
        },
        {
            "gender": "n",
            "name": "Ashrest"
        },
        {
            "gender": "n",
            "name": "Ashstead"
        },
        {
            "gender": "n",
            "name": "Ashton"
        },
        {
            "gender": "n",
            "name": "Ashview"
        },
        {
            "gender": "n",
            "name": "Ashville"
        },
        {
            "gender": "n",
            "name": "Ashwatch"
        },
        {
            "gender": "n",
            "name": "Ashwick"
        },
        {
            "gender": "n",
            "name": "Ashworth"
        },
        {
            "gender": "n",
            "name": "Ashy"
        },
        {
            "gender": "n",
            "name": "Ashbay"
        },
        {
            "gender": "n",
            "name": "Ashbridge"
        },
        {
            "gender": "n",
            "name": "Ashcastle"
        },
        {
            "gender": "n",
            "name": "Ashcliff"
        },
        {
            "gender": "n",
            "name": "Ashcross"
        },
        {
            "gender": "n",
            "name": "Briardale"
        },
        {
            "gender": "n",
            "name": "Briarford"
        },
        {
            "gender": "n",
            "name": "Briarburg"
        },
        {
            "gender": "n",
            "name": "Briarbury"
        },
        {
            "gender": "n",
            "name": "Briarhaven"
        },
        {
            "gender": "n",
            "name": "Briarhelm"
        },
        {
            "gender": "n",
            "name": "Briarhold"
        },
        {
            "gender": "n",
            "name": "Briarholt"
        },
        {
            "gender": "n",
            "name": "Briarkeep"
        },
        {
            "gender": "n",
            "name": "Briarland"
        },
        {
            "gender": "n",
            "name": "Briarmarch"
        },
        {
            "gender": "n",
            "name": "Briarmere"
        },
        {
            "gender": "n",
            "name": "Briarmont"
        },
        {
            "gender": "n",
            "name": "Briarmoor"
        },
        {
            "gender": "n",
            "name": "Briarmouth"
        },
        {
            "gender": "n",
            "name": "Briarport"
        },
        {
            "gender": "n",
            "name": "Briarrest"
        },
        {
            "gender": "n",
            "name": "Briarstead"
        },
        {
            "gender": "n",
            "name": "Briarton"
        },
        {
            "gender": "n",
            "name": "Briarview"
        },
        {
            "gender": "n",
            "name": "Briarville"
        },
        {
            "gender": "n",
            "name": "Briarwatch"
        },
        {
            "gender": "n",
            "name": "Briarwick"
        },
        {
            "gender": "n",
            "name": "Briarworth"
        },
        {
            "gender": "n",
            "name": "Briary"
        },
        {
            "gender": "n",
            "name": "Briarbay"
        },
        {
            "gender": "n",
            "name": "Briarbridge"
        },
        {
            "gender": "n",
            "name": "Briarcastle"
        },
        {
            "gender": "n",
            "name": "Briarcliff"
        },
        {
            "gender": "n",
            "name": "Briarcross"
        },
        {
            "gender": "n",
            "name": "Blackdale"
        },
        {
            "gender": "n",
            "name": "Blackford"
        },
        {
            "gender": "n",
            "name": "Blackburg"
        },
        {
            "gender": "n",
            "name": "Blackbury"
        },
        {
            "gender": "n",
            "name": "Blackhaven"
        },
        {
            "gender": "n",
            "name": "Blackhelm"
        },
        {
            "gender": "n",
            "name": "Blackhold"
        },
        {
            "gender": "n",
            "name": "Blackholt"
        },
        {
            "gender": "n",
            "name": "Blackkeep"
        },
        {
            "gender": "n",
            "name": "Blackland"
        },
        {
            "gender": "n",
            "name": "Blackmarch"
        },
        {
            "gender": "n",
            "name": "Blackmere"
        },
        {
            "gender": "n",
            "name": "Blackmont"
        },
        {
            "gender": "n",
            "name": "Blackmoor"
        },
        {
            "gender": "n",
            "name": "Blackmouth"
        },
        {
            "gender": "n",
            "name": "Blackport"
        },
        {
            "gender": "n",
            "name": "Blackrest"
        },
        {
            "gender": "n",
            "name": "Blackstead"
        },
        {
            "gender": "n",
            "name": "Blackton"
        },
        {
            "gender": "n",
            "name": "Blackview"
        },
        {
            "gender": "n",
            "name": "Blackville"
        },
        {
            "gender": "n",
            "name": "Blackwatch"
        },
        {
            "gender": "n",
            "name": "Blackwick"
        },
        {
            "gender": "n",
            "name": "Blackworth"
        },
        {
            "gender": "n",
            "name": "Blacky"
        },
        {
            "gender": "n",
            "name": "Blackbay"
        },
        {
            "gender": "n",
            "name": "Blackbridge"
        },
        {
            "gender": "n",
            "name": "Blackcastle"
        },
        {
            "gender": "n",
            "name": "Blackcliff"
        },
        {
            "gender": "n",
            "name": "Blackcross"
        },
        {
            "gender": "n",
            "name": "Bluedale"
        },
        {
            "gender": "n",
            "name": "Blueford"
        },
        {
            "gender": "n",
            "name": "Blueburg"
        },
        {
            "gender": "n",
            "name": "Bluebury"
        },
        {
            "gender": "n",
            "name": "Bluehaven"
        },
        {
            "gender": "n",
            "name": "Bluehelm"
        },
        {
            "gender": "n",
            "name": "Bluehold"
        },
        {
            "gender": "n",
            "name": "Blueholt"
        },
        {
            "gender": "n",
            "name": "Bluekeep"
        },
        {
            "gender": "n",
            "name": "Blueland"
        },
        {
            "gender": "n",
            "name": "Bluemarch"
        },
        {
            "gender": "n",
            "name": "Bluemere"
        },
        {
            "gender": "n",
            "name": "Bluemont"
        },
        {
            "gender": "n",
            "name": "Bluemoor"
        },
        {
            "gender": "n",
            "name": "Bluemouth"
        },
        {
            "gender": "n",
            "name": "Blueport"
        },
        {
            "gender": "n",
            "name": "Bluerest"
        },
        {
            "gender": "n",
            "name": "Bluestead"
        },
        {
            "gender": "n",
            "name": "Blueton"
        },
        {
            "gender": "n",
            "name": "Blueview"
        },
        {
            "gender": "n",
            "name": "Blueville"
        },
        {
            "gender": "n",
            "name": "Bluewatch"
        },
        {
            "gender": "n",
            "name": "Bluewick"
        },
        {
            "gender": "n",
            "name": "Blueworth"
        },
        {
            "gender": "n",
            "name": "Bluey"
        },
        {
            "gender": "n",
            "name": "Bluebay"
        },
        {
            "gender": "n",
            "name": "Bluebridge"
        },
        {
            "gender": "n",
            "name": "Bluecastle"
        },
        {
            "gender": "n",
            "name": "Bluecliff"
        },
        {
            "gender": "n",
            "name": "Bluecross"
        },
        {
            "gender": "n",
            "name": "Brightdale"
        },
        {
            "gender": "n",
            "name": "Brightford"
        },
        {
            "gender": "n",
            "name": "Brightburg"
        },
        {
            "gender": "n",
            "name": "Brightbury"
        },
        {
            "gender": "n",
            "name": "Brighthaven"
        },
        {
            "gender": "n",
            "name": "Brighthelm"
        },
        {
            "gender": "n",
            "name": "Brighthold"
        },
        {
            "gender": "n",
            "name": "Brightholt"
        },
        {
            "gender": "n",
            "name": "Brightkeep"
        },
        {
            "gender": "n",
            "name": "Brightland"
        },
        {
            "gender": "n",
            "name": "Brightmarch"
        },
        {
            "gender": "n",
            "name": "Brightmere"
        },
        {
            "gender": "n",
            "name": "Brightmont"
        },
        {
            "gender": "n",
            "name": "Brightmoor"
        },
        {
            "gender": "n",
            "name": "Brightmouth"
        },
        {
            "gender": "n",
            "name": "Brightport"
        },
        {
            "gender": "n",
            "name": "Brightrest"
        },
        {
            "gender": "n",
            "name": "Brightstead"
        },
        {
            "gender": "n",
            "name": "Brightton"
        },
        {
            "gender": "n",
            "name": "Brightview"
        },
        {
            "gender": "n",
            "name": "Brightville"
        },
        {
            "gender": "n",
            "name": "Brightwatch"
        },
        {
            "gender": "n",
            "name": "Brightwick"
        },
        {
            "gender": "n",
            "name": "Brightworth"
        },
        {
            "gender": "n",
            "name": "Brighty"
        },
        {
            "gender": "n",
            "name": "Brightbay"
        },
        {
            "gender": "n",
            "name": "Brightbridge"
        },
        {
            "gender": "n",
            "name": "Brightcastle"
        },
        {
            "gender": "n",
            "name": "Brightcliff"
        },
        {
            "gender": "n",
            "name": "Brightcross"
        },
        {
            "gender": "n",
            "name": "Cleardale"
        },
        {
            "gender": "n",
            "name": "Clearford"
        },
        {
            "gender": "n",
            "name": "Clearburg"
        },
        {
            "gender": "n",
            "name": "Clearbury"
        },
        {
            "gender": "n",
            "name": "Clearhaven"
        },
        {
            "gender": "n",
            "name": "Clearhelm"
        },
        {
            "gender": "n",
            "name": "Clearhold"
        },
        {
            "gender": "n",
            "name": "Clearholt"
        },
        {
            "gender": "n",
            "name": "Clearkeep"
        },
        {
            "gender": "n",
            "name": "Clearland"
        },
        {
            "gender": "n",
            "name": "Clearmarch"
        },
        {
            "gender": "n",
            "name": "Clearmere"
        },
        {
            "gender": "n",
            "name": "Clearmont"
        },
        {
            "gender": "n",
            "name": "Clearmoor"
        },
        {
            "gender": "n",
            "name": "Clearmouth"
        },
        {
            "gender": "n",
            "name": "Clearport"
        },
        {
            "gender": "n",
            "name": "Clearrest"
        },
        {
            "gender": "n",
            "name": "Clearstead"
        },
        {
            "gender": "n",
            "name": "Clearton"
        },
        {
            "gender": "n",
            "name": "Clearview"
        },
        {
            "gender": "n",
            "name": "Clearville"
        },
        {
            "gender": "n",
            "name": "Clearwatch"
        },
        {
            "gender": "n",
            "name": "Clearwick"
        },
        {
            "gender": "n",
            "name": "Clearworth"
        },
        {
            "gender": "n",
            "name": "Cleary"
        },
        {
            "gender": "n",
            "name": "Clearbay"
        },
        {
            "gender": "n",
            "name": "Clearbridge"
        },
        {
            "gender": "n",
            "name": "Clearcastle"
        },
        {
            "gender": "n",
            "name": "Clearcliff"
        },
        {
            "gender": "n",
            "name": "Clearcross"
        },
        {
            "gender": "n",
            "name": "Copperdale"
        },
        {
            "gender": "n",
            "name": "Copperford"
        },
        {
            "gender": "n",
            "name": "Copperburg"
        },
        {
            "gender": "n",
            "name": "Copperbury"
        },
        {
            "gender": "n",
            "name": "Copperhaven"
        },
        {
            "gender": "n",
            "name": "Copperhelm"
        },
        {
            "gender": "n",
            "name": "Copperhold"
        },
        {
            "gender": "n",
            "name": "Copperholt"
        },
        {
            "gender": "n",
            "name": "Copperkeep"
        },
        {
            "gender": "n",
            "name": "Copperland"
        },
        {
            "gender": "n",
            "name": "Coppermarch"
        },
        {
            "gender": "n",
            "name": "Coppermere"
        },
        {
            "gender": "n",
            "name": "Coppermont"
        },
        {
            "gender": "n",
            "name": "Coppermoor"
        },
        {
            "gender": "n",
            "name": "Coppermouth"
        },
        {
            "gender": "n",
            "name": "Copperport"
        },
        {
            "gender": "n",
            "name": "Copperrest"
        },
        {
            "gender": "n",
            "name": "Copperstead"
        },
        {
            "gender": "n",
            "name": "Copperton"
        },
        {
            "gender": "n",
            "name": "Copperview"
        },
        {
            "gender": "n",
            "name": "Copperville"
        },
        {
            "gender": "n",
            "name": "Copperwatch"
        },
        {
            "gender": "n",
            "name": "Copperwick"
        },
        {
            "gender": "n",
            "name": "Copperworth"
        },
        {
            "gender": "n",
            "name": "Coppery"
        },
        {
            "gender": "n",
            "name": "Copperbay"
        },
        {
            "gender": "n",
            "name": "Copperbridge"
        },
        {
            "gender": "n",
            "name": "Coppercastle"
        },
        {
            "gender": "n",
            "name": "Coppercliff"
        },
        {
            "gender": "n",
            "name": "Coppercross"
        },
        {
            "gender": "n",
            "name": "Dragondale"
        },
        {
            "gender": "n",
            "name": "Dragonford"
        },
        {
            "gender": "n",
            "name": "Dragonburg"
        },
        {
            "gender": "n",
            "name": "Dragonbury"
        },
        {
            "gender": "n",
            "name": "Dragonhaven"
        },
        {
            "gender": "n",
            "name": "Dragonhelm"
        },
        {
            "gender": "n",
            "name": "Dragonhold"
        },
        {
            "gender": "n",
            "name": "Dragonholt"
        },
        {
            "gender": "n",
            "name": "Dragonkeep"
        },
        {
            "gender": "n",
            "name": "Dragonland"
        },
        {
            "gender": "n",
            "name": "Dragonmarch"
        },
        {
            "gender": "n",
            "name": "Dragonmere"
        },
        {
            "gender": "n",
            "name": "Dragonmont"
        },
        {
            "gender": "n",
            "name": "Dragonmoor"
        },
        {
            "gender": "n",
            "name": "Dragonmouth"
        },
        {
            "gender": "n",
            "name": "Dragonport"
        },
        {
            "gender": "n",
            "name": "Dragonrest"
        },
        {
            "gender": "n",
            "name": "Dragonstead"
        },
        {
            "gender": "n",
            "name": "Dragonton"
        },
        {
            "gender": "n",
            "name": "Dragonview"
        },
        {
            "gender": "n",
            "name": "Dragonville"
        },
        {
            "gender": "n",
            "name": "Dragonwatch"
        },
        {
            "gender": "n",
            "name": "Dragonwick"
        },
        {
            "gender": "n",
            "name": "Dragonworth"
        },
        {
            "gender": "n",
            "name": "Dragony"
        },
        {
            "gender": "n",
            "name": "Dragonbay"
        },
        {
            "gender": "n",
            "name": "Dragonbridge"
        },
        {
            "gender": "n",
            "name": "Dragoncastle"
        },
        {
            "gender": "n",
            "name": "Dragoncliff"
        },
        {
            "gender": "n",
            "name": "Dragoncross"
        },
        {
            "gender": "n",
            "name": "Eagledale"
        },
        {
            "gender": "n",
            "name": "Eagleford"
        },
        {
            "gender": "n",
            "name": "Eagleburg"
        },
        {
            "gender": "n",
            "name": "Eaglebury"
        },
        {
            "gender": "n",
            "name": "Eaglehaven"
        },
        {
            "gender": "n",
            "name": "Eaglehelm"
        },
        {
            "gender": "n",
            "name": "Eaglehold"
        },
        {
            "gender": "n",
            "name": "Eagleholt"
        },
        {
            "gender": "n",
            "name": "Eaglekeep"
        },
        {
            "gender": "n",
            "name": "Eagleland"
        },
        {
            "gender": "n",
            "name": "Eaglemarch"
        },
        {
            "gender": "n",
            "name": "Eaglemere"
        },
        {
            "gender": "n",
            "name": "Eaglemont"
        },
        {
            "gender": "n",
            "name": "Eaglemoor"
        },
        {
            "gender": "n",
            "name": "Eaglemouth"
        },
        {
            "gender": "n",
            "name": "Eagleport"
        },
        {
            "gender": "n",
            "name": "Eaglerest"
        },
        {
            "gender": "n",
            "name": "Eaglestead"
        },
        {
            "gender": "n",
            "name": "Eagleton"
        },
        {
            "gender": "n",
            "name": "Eagleview"
        },
        {
            "gender": "n",
            "name": "Eagleville"
        },
        {
            "gender": "n",
            "name": "Eaglewatch"
        },
        {
            "gender": "n",
            "name": "Eaglewick"
        },
        {
            "gender": "n",
            "name": "Eagleworth"
        },
        {
            "gender": "n",
            "name": "Eagley"
        },
        {
            "gender": "n",
            "name": "Eaglebay"
        },
        {
            "gender": "n",
            "name": "Eaglebridge"
        },
        {
            "gender": "n",
            "name": "Eaglecastle"
        },
        {
            "gender": "n",
            "name": "Eaglecliff"
        },
        {
            "gender": "n",
            "name": "Eaglecross"
        },
        {
            "gender": "n",
            "name": "Falcondale"
        },
        {
            "gender": "n",
            "name": "Falconford"
        },
        {
            "gender": "n",
            "name": "Falconburg"
        },
        {
            "gender": "n",
            "name": "Falconbury"
        },
        {
            "gender": "n",
            "name": "Falconhaven"
        },
        {
            "gender": "n",
            "name": "Falconhelm"
        },
        {
            "gender": "n",
            "name": "Falconhold"
        },
        {
            "gender": "n",
            "name": "Falconholt"
        },
        {
            "gender": "n",
            "name": "Falconkeep"
        },
        {
            "gender": "n",
            "name": "Falconland"
        },
        {
            "gender": "n",
            "name": "Falconmarch"
        },
        {
            "gender": "n",
            "name": "Falconmere"
        },
        {
            "gender": "n",
            "name": "Falconmont"
        },
        {
            "gender": "n",
            "name": "Falconmoor"
        },
        {
            "gender": "n",
            "name": "Falconmouth"
        },
        {
            "gender": "n",
            "name": "Falconport"
        },
        {
            "gender": "n",
            "name": "Falconrest"
        },
        {
            "gender": "n",
            "name": "Falconstead"
        },
        {
            "gender": "n",
            "name": "Falconton"
        },
        {
            "gender": "n",
            "name": "Falconview"
        },
        {
            "gender": "n",
            "name": "Falconville"
        },
        {
            "gender": "n",
            "name": "Falconwatch"
        },
        {
            "gender": "n",
            "name": "Falconwick"
        },
        {
            "gender": "n",
            "name": "Falconworth"
        },
        {
            "gender": "n",
            "name": "Falcony"
        },
        {
            "gender": "n",
            "name": "Falconbay"
        },
        {
            "gender": "n",
            "name": "Falconbridge"
        },
        {
            "gender": "n",
            "name": "Falconcastle"
        },
        {
            "gender": "n",
            "name": "Falconcliff"
        },
        {
            "gender": "n",
            "name": "Falconcross"
        },
        {
            "gender": "n",
            "name": "Fairdale"
        },
        {
            "gender": "n",
            "name": "Fairford"
        },
        {
            "gender": "n",
            "name": "Fairburg"
        },
        {
            "gender": "n",
            "name": "Fairbury"
        },
        {
            "gender": "n",
            "name": "Fairhaven"
        },
        {
            "gender": "n",
            "name": "Fairhelm"
        },
        {
            "gender": "n",
            "name": "Fairhold"
        },
        {
            "gender": "n",
            "name": "Fairholt"
        },
        {
            "gender": "n",
            "name": "Fairkeep"
        },
        {
            "gender": "n",
            "name": "Fairland"
        },
        {
            "gender": "n",
            "name": "Fairmarch"
        },
        {
            "gender": "n",
            "name": "Fairmere"
        },
        {
            "gender": "n",
            "name": "Fairmont"
        },
        {
            "gender": "n",
            "name": "Fairmoor"
        },
        {
            "gender": "n",
            "name": "Fairmouth"
        },
        {
            "gender": "n",
            "name": "Fairport"
        },
        {
            "gender": "n",
            "name": "Fairrest"
        },
        {
            "gender": "n",
            "name": "Fairstead"
        },
        {
            "gender": "n",
            "name": "Fairton"
        },
        {
            "gender": "n",
            "name": "Fairview"
        },
        {
            "gender": "n",
            "name": "Fairville"
        },
        {
            "gender": "n",
            "name": "Fairwatch"
        },
        {
            "gender": "n",
            "name": "Fairwick"
        },
        {
            "gender": "n",
            "name": "Fairworth"
        },
        {
            "gender": "n",
            "name": "Fairy"
        },
        {
            "gender": "n",
            "name": "Fairbay"
        },
        {
            "gender": "n",
            "name": "Fairbridge"
        },
        {
            "gender": "n",
            "name": "Faircastle"
        },
        {
            "gender": "n",
            "name": "Faircliff"
        },
        {
            "gender": "n",
            "name": "Faircross"
        },
        {
            "gender": "n",
            "name": "Ferndale"
        },
        {
            "gender": "n",
            "name": "Fernford"
        },
        {
            "gender": "n",
            "name": "Fernburg"
        },
        {
            "gender": "n",
            "name": "Fernbury"
        },
        {
            "gender": "n",
            "name": "Fernhaven"
        },
        {
            "gender": "n",
            "name": "Fernhelm"
        },
        {
            "gender": "n",
            "name": "Fernhold"
        },
        {
            "gender": "n",
            "name": "Fernholt"
        },
        {
            "gender": "n",
            "name": "Fernkeep"
        },
        {
            "gender": "n",
            "name": "Fernland"
        },
        {
            "gender": "n",
            "name": "Fernmarch"
        },
        {
            "gender": "n",
            "name": "Fernmere"
        },
        {
            "gender": "n",
            "name": "Fernmont"
        },
        {
            "gender": "n",
            "name": "Fernmoor"
        },
        {
            "gender": "n",
            "name": "Fernmouth"
        },
        {
            "gender": "n",
            "name": "Fernport"
        },
        {
            "gender": "n",
            "name": "Fernrest"
        },
        {
            "gender": "n",
            "name": "Fernstead"
        },
        {
            "gender": "n",
            "name": "Fernton"
        },
        {
            "gender": "n",
            "name": "Fernview"
        },
        {
            "gender": "n",
            "name": "Fernville"
        },
        {
            "gender": "n",
            "name": "Fernwatch"
        },
        {
            "gender": "n",
            "name": "Fernwick"
        },
        {
            "gender": "n",
            "name": "Fernworth"
        },
        {
            "gender": "n",
            "name": "Ferny"
        },
        {
            "gender": "n",
            "name": "Fernbay"
        },
        {
            "gender": "n",
            "name": "Fernbridge"
        },
        {
            "gender": "n",
            "name": "Ferncastle"
        },
        {
            "gender": "n",
            "name": "Ferncliff"
        },
        {
            "gender": "n",
            "name": "Ferncross"
        },
        {
            "gender": "n",
            "name": "Frostdale"
        },
        {
            "gender": "n",
            "name": "Frostford"
        },
        {
            "gender": "n",
            "name": "Frostburg"
        },
        {
            "gender": "n",
            "name": "Frostbury"
        },
        {
            "gender": "n",
            "name": "Frosthaven"
        },
        {
            "gender": "n",
            "name": "Frosthelm"
        },
        {
            "gender": "n",
            "name": "Frosthold"
        },
        {
            "gender": "n",
            "name": "Frostholt"
        },
        {
            "gender": "n",
            "name": "Frostkeep"
        },
        {
            "gender": "n",
            "name": "Frostland"
        },
        {
            "gender": "n",
            "name": "Frostmarch"
        },
        {
            "gender": "n",
            "name": "Frostmere"
        },
        {
            "gender": "n",
            "name": "Frostmont"
        },
        {
            "gender": "n",
            "name": "Frostmoor"
        },
        {
            "gender": "n",
            "name": "Frostmouth"
        },
        {
            "gender": "n",
            "name": "Frostport"
        },
        {
            "gender": "n",
            "name": "Frostrest"
        },
        {
            "gender": "n",
            "name": "Froststead"
        },
        {
            "gender": "n",
            "name": "Frostton"
        },
        {
            "gender": "n",
            "name": "Frostview"
        },
        {
            "gender": "n",
            "name": "Frostville"
        },
        {
            "gender": "n",
            "name": "Frostwatch"
        },
        {
            "gender": "n",
            "name": "Frostwick"
        },
        {
            "gender": "n",
            "name": "Frostworth"
        },
        {
            "gender": "n",
            "name": "Frosty"
        },
        {
            "gender": "n",
            "name": "Frostbay"
        },
        {
            "gender": "n",
            "name": "Frostbridge"
        },
        {
            "gender": "n",
            "name": "Frostcastle"
        },
        {
            "gender": "n",
            "name": "Frostcliff"
        },
        {
            "gender": "n",
            "name": "Frostcross"
        },
        {
            "gender": "n",
            "name": "Golddale"
        },
        {
            "gender": "n",
            "name": "Goldford"
        },
        {
            "gender": "n",
            "name": "Goldburg"
        },
        {
            "gender": "n",
            "name": "Goldbury"
        },
        {
            "gender": "n",
            "name": "Goldhaven"
        },
        {
            "gender": "n",
            "name": "Goldhelm"
        },
        {
            "gender": "n",
            "name": "Goldhold"
        },
        {
            "gender": "n",
            "name": "Goldholt"
        },
        {
            "gender": "n",
            "name": "Goldkeep"
        },
        {
            "gender": "n",
            "name": "Goldland"
        },
        {
            "gender": "n",
            "name": "Goldmarch"
        },
        {
            "gender": "n",
            "name": "Goldmere"
        },
        {
            "gender": "n",
            "name": "Goldmont"
        },
        {
            "gender": "n",
            "name": "Goldmoor"
        },
        {
            "gender": "n",
            "name": "Goldmouth"
        },
        {
            "gender": "n",
            "name": "Goldport"
        },
        {
            "gender": "n",
            "name": "Goldrest"
        },
        {
            "gender": "n",
            "name": "Goldstead"
        },
        {
            "gender": "n",
            "name": "Goldton"
        },
        {
            "gender": "n",
            "name": "Goldview"
        },
        {
            "gender": "n",
            "name": "Goldville"
        },
        {
            "gender": "n",
            "name": "Goldwatch"
        },
        {
            "gender": "n",
            "name": "Goldwick"
        },
        {
            "gender": "n",
            "name": "Goldworth"
        },
        {
            "gender": "n",
            "name": "Goldy"
        },
        {
            "gender": "n",
            "name": "Goldbay"
        },
        {
            "gender": "n",
            "name": "Goldbridge"
        },
        {
            "gender": "n",
            "name": "Goldcastle"
        },
        {
            "gender": "n",
            "name": "Goldcliff"
        },
        {
            "gender": "n",
            "name": "Goldcross"
        },
        {
            "gender": "n",
            "name": "Greendale"
        },
        {
            "gender": "n",
            "name": "Greenford"
        },
        {
            "gender": "n",
            "name": "Greenburg"
        },
        {
            "gender": "n",
            "name": "Greenbury"
        },
        {
            "gender": "n",
            "name": "Greenhaven"
        },
        {
            "gender": "n",
            "name": "Greenhelm"
        },
        {
            "gender": "n",
            "name": "Greenhold"
        },
        {
            "gender": "n",
            "name": "Greenholt"
        },
        {
            "gender": "n",
            "name": "Greenkeep"
        },
        {
            "gender": "n",
            "name": "Greenland"
        },
        {
            "gender": "n",
            "name": "Greenmarch"
        },
        {
            "gender": "n",
            "name": "Greenmere"
        },
        {
            "gender": "n",
            "name": "Greenmont"
        },
        {
            "gender": "n",
            "name": "Greenmoor"
        },
        {
            "gender": "n",
            "name": "Greenmouth"
        },
        {
            "gender": "n",
            "name": "Greenport"
        },
        {
            "gender": "n",
            "name": "Greenrest"
        },
        {
            "gender": "n",
            "name": "Greenstead"
        },
        {
            "gender": "n",
            "name": "Greenton"
        },
        {
            "gender": "n",
            "name": "Greenview"
        },
        {
            "gender": "n",
            "name": "Greenville"
        },
        {
            "gender": "n",
            "name": "Greenwatch"
        },
        {
            "gender": "n",
            "name": "Greenwick"
        },
        {
            "gender": "n",
            "name": "Greenworth"
        },
        {
            "gender": "n",
            "name": "Greeny"
        },
        {
            "gender": "n",
            "name": "Greenbay"
        },
        {
            "gender": "n",
            "name": "Greenbridge"
        },
        {
            "gender": "n",
            "name": "Greencastle"
        },
        {
            "gender": "n",
            "name": "Greencliff"
        },
        {
            "gender": "n",
            "name": "Greencross"
        },
        {
            "gender": "n",
            "name": "Hartdale"
        },
        {
            "gender": "n",
            "name": "Hartford"
        },
        {
            "gender": "n",
            "name": "Hartburg"
        },
        {
            "gender": "n",
            "name": "Hartbury"
        },
        {
            "gender": "n",
            "name": "Harthaven"
        },
        {
            "gender": "n",
            "name": "Harthelm"
        },
        {
            "gender": "n",
            "name": "Harthold"
        },
        {
            "gender": "n",
            "name": "Hartholt"
        },
        {
            "gender": "n",
            "name": "Hartkeep"
        },
        {
            "gender": "n",
            "name": "Hartland"
        },
        {
            "gender": "n",
            "name": "Hartmarch"
        },
        {
            "gender": "n",
            "name": "Hartmere"
        },
        {
            "gender": "n",
            "name": "Hartmont"
        },
        {
            "gender": "n",
            "name": "Hartmoor"
        },
        {
            "gender": "n",
            "name": "Hartmouth"
        },
        {
            "gender": "n",
            "name": "Hartport"
        },
        {
            "gender": "n",
            "name": "Hartrest"
        },
        {
            "gender": "n",
            "name": "Hartstead"
        },
        {
            "gender": "n",
            "name": "Hartton"
        },
        {
            "gender": "n",
            "name": "Hartview"
        },
        {
            "gender": "n",
            "name": "Hartville"
        },
        {
            "gender": "n",
            "name": "Hartwatch"
        },
        {
            "gender": "n",
            "name": "Hartwick"
        },
        {
            "gender": "n",
            "name": "Hartworth"
        },
        {
            "gender": "n",
            "name": "Harty"
        },
        {
            "gender": "n",
            "name": "Hartbay"
        },
        {
            "gender": "n",
            "name": "Hartbridge"
        },
        {
            "gender": "n",
            "name": "Hartcastle"
        },
        {
            "gender": "n",
            "name": "Hartcliff"
        },
        {
            "gender": "n",
            "name": "Hartcross"
        },
        {
            "gender": "n",
            "name": "Highdale"
        },
        {
            "gender": "n",
            "name": "Highford"
        },
        {
            "gender": "n",
            "name": "Highburg"
        },
        {
            "gender": "n",
            "name": "Highbury"
        },
        {
            "gender": "n",
            "name": "Highhaven"
        },
        {
            "gender": "n",
            "name": "Highhelm"
        },
        {
            "gender": "n",
            "name": "Highhold"
        },
        {
            "gender": "n",
            "name": "Highholt"
        },
        {
            "gender": "n",
            "name": "Highkeep"
        },
        {
            "gender": "n",
            "name": "Highland"
        },
        {
            "gender": "n",
            "name": "Highmarch"
        },
        {
            "gender": "n",
            "name": "Highmere"
        },
        {
            "gender": "n",
            "name": "Highmont"
        },
        {
            "gender": "n",
            "name": "Highmoor"
        },
        {
            "gender": "n",
            "name": "Highmouth"
        },
        {
            "gender": "n",
            "name": "Highport"
        },
        {
            "gender": "n",
            "name": "Highrest"
        },
        {
            "gender": "n",
            "name": "Highstead"
        },
        {
            "gender": "n",
            "name": "Highton"
        },
        {
            "gender": "n",
            "name": "Highview"
        },
        {
            "gender": "n",
            "name": "Highville"
        },
        {
            "gender": "n",
            "name": "Highwatch"
        },
        {
            "gender": "n",
            "name": "Highwick"
        },
        {
            "gender": "n",
            "name": "Highworth"
        },
        {
            "gender": "n",
            "name": "Highy"
        },
        {
            "gender": "n",
            "name": "Highbay"
        },
        {
            "gender": "n",
            "name": "Highbridge"
        },
        {
            "gender": "n",
            "name": "Highcastle"
        },
        {
            "gender": "n",
            "name": "Highcliff"
        },
        {
            "gender": "n",
            "name": "Highcross"
        },
        {
            "gender": "n",
            "name": "Irondale"
        },
        {
            "gender": "n",
            "name": "Ironford"
        },
        {
            "gender": "n",
            "name": "Ironburg"
        },
        {
            "gender": "n",
            "name": "Ironbury"
        },
        {
            "gender": "n",
            "name": "Ironhaven"
        },
        {
            "gender": "n",
            "name": "Ironhelm"
        },
        {
            "gender": "n",
            "name": "Ironhold"
        },
        {
            "gender": "n",
            "name": "Ironholt"
        },
        {
            "gender": "n",
            "name": "Ironkeep"
        },
        {
            "gender": "n",
            "name": "Ironland"
        },
        {
            "gender": "n",
            "name": "Ironmarch"
        },
        {
            "gender": "n",
            "name": "Ironmere"
        },
        {
            "gender": "n",
            "name": "Ironmont"
        },
        {
            "gender": "n",
            "name": "Ironmoor"
        },
        {
            "gender": "n",
            "name": "Ironmouth"
        },
        {
            "gender": "n",
            "name": "Ironport"
        },
        {
            "gender": "n",
            "name": "Ironrest"
        },
        {
            "gender": "n",
            "name": "Ironstead"
        },
        {
            "gender": "n",
            "name": "Ironton"
        },
        {
            "gender": "n",
            "name": "Ironview"
        },
        {
            "gender": "n",
            "name": "Ironville"
        },
        {
            "gender": "n",
            "name": "Ironwatch"
        },
        {
            "gender": "n",
            "name": "Ironwick"
        },
        {
            "gender": "n",
            "name": "Ironworth"
        },
        {
            "gender": "n",
            "name": "Irony"
        },
        {
            "gender": "n",
            "name": "Ironbay"
        },
        {
            "gender": "n",
            "name": "Ironbridge"
        },
        {
            "gender": "n",
            "name": "Ironcastle"
        },
        {
            "gender": "n",
            "name": "Ironcliff"
        },
        {
            "gender": "n",
            "name": "Ironcross"
        },
        {
            "gender": "n",
            "name": "Lakedale"
        },
        {
            "gender": "n",
            "name": "Lakeford"
        },
        {
            "gender": "n",
            "name": "Lakeburg"
        },
        {
            "gender": "n",
            "name": "Lakebury"
        },
        {
            "gender": "n",
            "name": "Lakehaven"
        },
        {
            "gender": "n",
            "name": "Lakehelm"
        },
        {
            "gender": "n",
            "name": "Lakehold"
        },
        {
            "gender": "n",
            "name": "Lakeholt"
        },
        {
            "gender": "n",
            "name": "Lakekeep"
        },
        {
            "gender": "n",
            "name": "Lakeland"
        },
        {
            "gender": "n",
            "name": "Lakemarch"
        },
        {
            "gender": "n",
            "name": "Lakemere"
        },
        {
            "gender": "n",
            "name": "Lakemont"
        },
        {
            "gender": "n",
            "name": "Lakemoor"
        },
        {
            "gender": "n",
            "name": "Lakemouth"
        },
        {
            "gender": "n",
            "name": "Lakeport"
        },
        {
            "gender": "n",
            "name": "Lakerest"
        },
        {
            "gender": "n",
            "name": "Lakestead"
        },
        {
            "gender": "n",
            "name": "Laketon"
        },
        {
            "gender": "n",
            "name": "Lakeview"
        },
        {
            "gender": "n",
            "name": "Lakeville"
        },
        {
            "gender": "n",
            "name": "Lakewatch"
        },
        {
            "gender": "n",
            "name": "Lakewick"
        },
        {
            "gender": "n",
            "name": "Lakeworth"
        },
        {
            "gender": "n",
            "name": "Lakey"
        },
        {
            "gender": "n",
            "name": "Lakebay"
        },
        {
            "gender": "n",
            "name": "Lakebridge"
        },
        {
            "gender": "n",
            "name": "Lakecastle"
        },
        {
            "gender": "n",
            "name": "Lakecliff"
        },
        {
            "gender": "n",
            "name": "Lakecross"
        },
        {
            "gender": "n",
            "name": "Lowdale"
        },
        {
            "gender": "n",
            "name": "Lowford"
        },
        {
            "gender": "n",
            "name": "Lowburg"
        },
        {
            "gender": "n",
            "name": "Lowbury"
        },
        {
            "gender": "n",
            "name": "Lowhaven"
        },
        {
            "gender": "n",
            "name": "Lowhelm"
        },
        {
            "gender": "n",
            "name": "Lowhold"
        },
        {
            "gender": "n",
            "name": "Lowholt"
        },
        {
            "gender": "n",
            "name": "Lowkeep"
        },
        {
            "gender": "n",
            "name": "Lowland"
        },
        {
            "gender": "n",
            "name": "Lowmarch"
        },
        {
            "gender": "n",
            "name": "Lowmere"
        },
        {
            "gender": "n",
            "name": "Lowmont"
        },
        {
            "gender": "n",
            "name": "Lowmoor"
        },
        {
            "gender": "n",
            "name": "Lowmouth"
        },
        {
            "gender": "n",
            "name": "Lowport"
        },
        {
            "gender": "n",
            "name": "Lowrest"
        },
        {
            "gender": "n",
            "name": "Lowstead"
        },
        {
            "gender": "n",
            "name": "Lowton"
        },
        {
            "gender": "n",
            "name": "Lowview"
        },
        {
            "gender": "n",
            "name": "Lowville"
        },
        {
            "gender": "n",
            "name": "Lowwatch"
        },
        {
            "gender": "n",
            "name": "Lowwick"
        },
        {
            "gender": "n",
            "name": "Lowworth"
        },
        {
            "gender": "n",
            "name": "Lowy"
        },
        {
            "gender": "n",
            "name": "Lowbay"
        },
        {
            "gender": "n",
            "name": "Lowbridge"
        },
        {
            "gender": "n",
            "name": "Lowcastle"
        },
        {
            "gender": "n",
            "name": "Lowcliff"
        },
        {
            "gender": "n",
            "name": "Lowcross"
        },
        {
            "gender": "n",
            "name": "Moordale"
        },
        {
            "gender": "n",
            "name": "Moorford"
        },
        {
            "gender": "n",
            "name": "Moorburg"
        },
        {
            "gender": "n",
            "name": "Moorbury"
        },
        {
            "gender": "n",
            "name": "Moorhaven"
        },
        {
            "gender": "n",
            "name": "Moorhelm"
        },
        {
            "gender": "n",
            "name": "Moorhold"
        },
        {
            "gender": "n",
            "name": "Moorholt"
        },
        {
            "gender": "n",
            "name": "Moorkeep"
        },
        {
            "gender": "n",
            "name": "Moorland"
        },
        {
            "gender": "n",
            "name": "Moormarch"
        },
        {
            "gender": "n",
            "name": "Moormere"
        },
        {
            "gender": "n",
            "name": "Moormont"
        },
        {
            "gender": "n",
            "name": "Moormoor"
        },
        {
            "gender": "n",
            "name": "Moormouth"
        },
        {
            "gender": "n",
            "name": "Moorport"
        },
        {
            "gender": "n",
            "name": "Moorrest"
        },
        {
            "gender": "n",
            "name": "Moorstead"
        },
        {
            "gender": "n",
            "name": "Moorton"
        },
        {
            "gender": "n",
            "name": "Moorview"
        },
        {
            "gender": "n",
            "name": "Moorville"
        },
        {
            "gender": "n",
            "name": "Moorwatch"
        },
        {
            "gender": "n",
            "name": "Moorwick"
        },
        {
            "gender": "n",
            "name": "Moorworth"
        },
        {
            "gender": "n",
            "name": "Moory"
        },
        {
            "gender": "n",
            "name": "Moorbay"
        },
        {
            "gender": "n",
            "name": "Moorbridge"
        },
        {
            "gender": "n",
            "name": "Moorcastle"
        },
        {
            "gender": "n",
            "name": "Moorcliff"
        },
        {
            "gender": "n",
            "name": "Moorcross"
        },
        {
            "gender": "n",
            "name": "Oakdale"
        },
        {
            "gender": "n",
            "name": "Oakford"
        },
        {
            "gender": "n",
            "name": "Oakburg"
        },
        {
            "gender": "n",
            "name": "Oakbury"
        },
        {
            "gender": "n",
            "name": "Oakhaven"
        },
        {
            "gender": "n",
            "name": "Oakhelm"
        },
        {
            "gender": "n",
            "name": "Oakhold"
        },
        {
            "gender": "n",
            "name": "Oakholt"
        },
        {
            "gender": "n",
            "name": "Oakkeep"
        },
        {
            "gender": "n",
            "name": "Oakland"
        },
        {
            "gender": "n",
            "name": "Oakmarch"
        },
        {
            "gender": "n",
            "name": "Oakmere"
        },
        {
            "gender": "n",
            "name": "Oakmont"
        },
        {
            "gender": "n",
            "name": "Oakmoor"
        },
        {
            "gender": "n",
            "name": "Oakmouth"
        },
        {
            "gender": "n",
            "name": "Oakport"
        },
        {
            "gender": "n",
            "name": "Oakrest"
        },
        {
            "gender": "n",
            "name": "Oakstead"
        },
        {
            "gender": "n",
            "name": "Oakton"
        },
        {
            "gender": "n",
            "name": "Oakview"
        },
        {
            "gender": "n",
            "name": "Oakville"
        },
        {
            "gender": "n",
            "name": "Oakwatch"
        },
        {
            "gender": "n",
            "name": "Oakwick"
        },
        {
            "gender": "n",
            "name": "Oakworth"
        },
        {
            "gender": "n",
            "name": "Oaky"
        },
        {
            "gender": "n",
            "name": "Oakbay"
        },
        {
            "gender": "n",
            "name": "Oakbridge"
        },
        {
            "gender": "n",
            "name": "Oakcastle"
        },
        {
            "gender": "n",
            "name": "Oakcliff"
        },
        {
            "gender": "n",
            "name": "Oakcross"
        },
        {
            "gender": "n",
            "name": "Pinedale"
        },
        {
            "gender": "n",
            "name": "Pineford"
        },
        {
            "gender": "n",
            "name": "Pineburg"
        },
        {
            "gender": "n",
            "name": "Pinebury"
        },
        {
            "gender": "n",
            "name": "Pinehaven"
        },
        {
            "gender": "n",
            "name": "Pinehelm"
        },
        {
            "gender": "n",
            "name": "Pinehold"
        },
        {
            "gender": "n",
            "name": "Pineholt"
        },
        {
            "gender": "n",
            "name": "Pinekeep"
        },
        {
            "gender": "n",
            "name": "Pineland"
        },
        {
            "gender": "n",
            "name": "Pinemarch"
        },
        {
            "gender": "n",
            "name": "Pinemere"
        },
        {
            "gender": "n",
            "name": "Pinemont"
        },
        {
            "gender": "n",
            "name": "Pinemoor"
        },
        {
            "gender": "n",
            "name": "Pinemouth"
        },
        {
            "gender": "n",
            "name": "Pineport"
        },
        {
            "gender": "n",
            "name": "Pinerest"
        },
        {
            "gender": "n",
            "name": "Pinestead"
        },
        {
            "gender": "n",
            "name": "Pineton"
        },
        {
            "gender": "n",
            "name": "Pineview"
        },
        {
            "gender": "n",
            "name": "Pineville"
        },
        {
            "gender": "n",
            "name": "Pinewatch"
        },
        {
            "gender": "n",
            "name": "Pinewick"
        },
        {
            "gender": "n",
            "name": "Pineworth"
        },
        {
            "gender": "n",
            "name": "Piney"
        },
        {
            "gender": "n",
            "name": "Pinebay"
        },
        {
            "gender": "n",
            "name": "Pinebridge"
        },
        {
            "gender": "n",
            "name": "Pinecastle"
        },
        {
            "gender": "n",
            "name": "Pinecliff"
        },
        {
            "gender": "n",
            "name": "Pinecross"
        },
        {
            "gender": "n",
            "name": "Reddale"
        },
        {
            "gender": "n",
            "name": "Redford"
        },
        {
            "gender": "n",
            "name": "Redburg"
        },
        {
            "gender": "n",
            "name": "Redbury"
        },
        {
            "gender": "n",
            "name": "Redhaven"
        },
        {
            "gender": "n",
            "name": "Redhelm"
        },
        {
            "gender": "n",
            "name": "Redhold"
        },
        {
            "gender": "n",
            "name": "Redholt"
        },
        {
            "gender": "n",
            "name": "Redkeep"
        },
        {
            "gender": "n",
            "name": "Redland"
        },
        {
            "gender": "n",
            "name": "Redmarch"
        },
        {
            "gender": "n",
            "name": "Redmere"
        },
        {
            "gender": "n",
            "name": "Redmont"
        },
        {
            "gender": "n",
            "name": "Redmoor"
        },
        {
            "gender": "n",
            "name": "Redmouth"
        },
        {
            "gender": "n",
            "name": "Redport"
        },
        {
            "gender": "n",
            "name": "Redrest"
        },
        {
            "gender": "n",
            "name": "Redstead"
        },
        {
            "gender": "n",
            "name": "Redton"
        },
        {
            "gender": "n",
            "name": "Redview"
        },
        {
            "gender": "n",
            "name": "Redville"
        },
        {
            "gender": "n",
            "name": "Redwatch"
        },
        {
            "gender": "n",
            "name": "Redwick"
        },
        {
            "gender": "n",
            "name": "Redworth"
        },
        {
            "gender": "n",
            "name": "Redy"
        },
        {
            "gender": "n",
            "name": "Redbay"
        },
        {
            "gender": "n",
            "name": "Redbridge"
        },
        {
            "gender": "n",
            "name": "Redcastle"
        },
        {
            "gender": "n",
            "name": "Redcliff"
        },
        {
            "gender": "n",
            "name": "Redcross"
        },
        {
            "gender": "n",
            "name": "Riverdale"
        },
        {
            "gender": "n",
            "name": "Riverford"
        },
        {
            "gender": "n",
            "name": "Riverburg"
        },
        {
            "gender": "n",
            "name": "Riverbury"
        },
        {
            "gender": "n",
            "name": "Riverhaven"
        },
        {
            "gender": "n",
            "name": "Riverhelm"
        },
        {
            "gender": "n",
            "name": "Riverhold"
        },
        {
            "gender": "n",
            "name": "Riverholt"
        },
        {
            "gender": "n",
            "name": "Riverkeep"
        },
        {
            "gender": "n",
            "name": "Riverland"
        },
        {
            "gender": "n",
            "name": "Rivermarch"
        },
        {
            "gender": "n",
            "name": "Rivermere"
        },
        {
            "gender": "n",
            "name": "Rivermont"
        },
        {
            "gender": "n",
            "name": "Rivermoor"
        },
        {
            "gender": "n",
            "name": "Rivermouth"
        },
        {
            "gender": "n",
            "name": "Riverport"
        },
        {
            "gender": "n",
            "name": "Riverrest"
        },
        {
            "gender": "n",
            "name": "Riverstead"
        },
        {
            "gender": "n",
            "name": "Riverton"
        },
        {
            "gender": "n",
            "name": "Riverview"
        },
        {
            "gender": "n",
            "name": "Riverville"
        },
        {
            "gender": "n",
            "name": "Riverwatch"
        },
        {
            "gender": "n",
            "name": "Riverwick"
        },
        {
            "gender": "n",
            "name": "Riverworth"
        },
        {
            "gender": "n",
            "name": "Rivery"
        },
        {
            "gender": "n",
            "name": "Riverbay"
        },
        {
            "gender": "n",
            "name": "Riverbridge"
        },
        {
            "gender": "n",
            "name": "Rivercastle"
        },
        {
            "gender": "n",
            "name": "Rivercliff"
        },
        {
            "gender": "n",
            "name": "Rivercross"
        },
        {
            "gender": "n",
            "name": "Silverdale"
        },
        {
            "gender": "n",
            "name": "Silverford"
        },
        {
            "gender": "n",
            "name": "Silverburg"
        },
        {
            "gender": "n",
            "name": "Silverbury"
        },
        {
            "gender": "n",
            "name": "Silverhaven"
        },
        {
            "gender": "n",
            "name": "Silverhelm"
        },
        {
            "gender": "n",
            "name": "Silverhold"
        },
        {
            "gender": "n",
            "name": "Silverholt"
        },
        {
            "gender": "n",
            "name": "Silverkeep"
        },
        {
            "gender": "n",
            "name": "Silverland"
        },
        {
            "gender": "n",
            "name": "Silvermarch"
        },
        {
            "gender": "n",
            "name": "Silvermere"
        },
        {
            "gender": "n",
            "name": "Silvermont"
        },
        {
            "gender": "n",
            "name": "Silvermoor"
        },
        {
            "gender": "n",
            "name": "Silvermouth"
        },
        {
            "gender": "n",
            "name": "Silverport"
        },
        {
            "gender": "n",
            "name": "Silverrest"
        },
        {
            "gender": "n",
            "name": "Silverstead"
        },
        {
            "gender": "n",
            "name": "Silverton"
        },
        {
            "gender": "n",
            "name": "Silverview"
        },
        {
            "gender": "n",
            "name": "Silverville"
        },
        {
            "gender": "n",
            "name": "Silverwatch"
        },
        {
            "gender": "n",
            "name": "Silverwick"
        },
        {
            "gender": "n",
            "name": "Silverworth"
        },
        {
            "gender": "n",
            "name": "Silvery"
        },
        {
            "gender": "n",
            "name": "Silverbay"
        },
        {
            "gender": "n",
            "name": "Silverbridge"
        },
        {
            "gender": "n",
            "name": "Silvercastle"
        },
        {
            "gender": "n",
            "name": "Silvercliff"
        },
        {
            "gender": "n",
            "name": "Silvercross"
        },
        {
            "gender": "n",
            "name": "Stonedale"
        },
        {
            "gender": "n",
            "name": "Stoneford"
        },
        {
            "gender": "n",
            "name": "Stoneburg"
        },
        {
            "gender": "n",
            "name": "Stonebury"
        },
        {
            "gender": "n",
            "name": "Stonehaven"
        },
        {
            "gender": "n",
            "name": "Stonehelm"
        },
        {
            "gender": "n",
            "name": "Stonehold"
        },
        {
            "gender": "n",
            "name": "Stoneholt"
        }
    ]
}